arpreq.pypy37-pp73-x86_64-linux-gnu.so
arpreq-0.3.4.dist-info/LICENSE
arpreq-0.3.4.dist-info/METADATA
arpreq-0.3.4.dist-info/WHEEL
arpreq-0.3.4.dist-info/top_level.txt
arpreq-0.3.4.dist-info/RECORD
